[
  {
    "homeBannerId": 48,
    "seq": 9998,
    "homeBannerType": "general",
    "name": "Welcome Show Banner",
    "assetbundleName": "banner_virtuallive1",
    "transitionDestinationType": "virtual_live",
    "transitionDestinationId": 20001,
    "startAt": 1601496000000,
    "endAt": 4102473599000
  },
  {
    "homeBannerId": 409,
    "seq": 100,
    "homeBannerType": "event",
    "name": "[イベント]レオ二箱イベ8巡目_イベントバナー",
    "assetbundleName": "event_memories_2022",
    "transitionDestinationType": "event",
    "transitionDestinationId": 56,
    "startAt": 1682114400000,
    "endAt": 1682891999000
  },
  {
    "homeBannerId": 414,
    "seq": 130,
    "homeBannerType": "general",
    "name": "Ena Shinonome Happy Birthday Gacha",
    "assetbundleName": "banner_gacha204",
    "transitionDestinationType": "gacha",
    "transitionDestinationId": 204,
    "startAt": 1682838000000,
    "endAt": 1683442799000
  },
  {
    "homeBannerId": 415,
    "seq": 110,
    "homeBannerType": "general",
    "name": "[ガチャ]モモジャン箱イベ8巡目_定常ガチャバナー",
    "assetbundleName": "banner_gacha205",
    "transitionDestinationType": "gacha",
    "transitionDestinationId": 205,
    "startAt": 1682881200000,
    "endAt": 1683745199000
  },
  {
    "homeBannerId": 1001,
    "seq": 200,
    "homeBannerType": "general",
    "name": "Colorful++(サブスクリプション)",
    "assetbundleName": "banner_subscription",
    "transitionDestinationType": "subscription",
    "transitionDestinationId": 1,
    "startAt": 1633118400000,
    "endAt": 4102473540000
  },
  {
    "homeBannerId": 1039,
    "seq": 30,
    "homeBannerType": "general",
    "name": "4★ Guaranteed Gacha",
    "assetbundleName": "banner_gacha1030",
    "transitionDestinationType": "gacha",
    "transitionDestinationId": 1030,
    "startAt": 1681758000000,
    "endAt": 1682967599000
  },
  {
    "homeBannerId": 1042,
    "seq": 220,
    "homeBannerType": "general",
    "name": "「スイーツ」再販売",
    "assetbundleName": "banner_shop_costume_resale_en_2023_04",
    "transitionDestinationType": "billing_shop_for_jewel",
    "startAt": 1680332400000,
    "endAt": 1682924399000
  },
  {
    "homeBannerId": 1045,
    "seq": 190,
    "homeBannerType": "general",
    "name": "「犬」衣装 全カラー",
    "assetbundleName": "banner_shop_costume_sale_en_05",
    "transitionDestinationType": "billing_shop_for_jewel",
    "startAt": 1682460000000,
    "endAt": 1685084399000
  }
]